img_dataset_builder/__init__.py
img_dataset_builder/cli.py
img_dataset_builder/config.py
img_dataset_builder/config.yaml
img_dataset_builder/core.py
img_dataset_builder/helper.py
vision_dataset_builder-0.9.dist-info/LICENSE
vision_dataset_builder-0.9.dist-info/METADATA
vision_dataset_builder-0.9.dist-info/WHEEL
vision_dataset_builder-0.9.dist-info/entry_points.txt
vision_dataset_builder-0.9.dist-info/top_level.txt
vision_dataset_builder-0.9.dist-info/RECORD
