Metadata-Version: 2.1
Name: vision-dataset-builder
Version: 0.9
Summary: A simple package to create image datasets for computer vision models.
Home-page: https://github.com/yrangana/img_dataset_builder
Author: Yasiru Rangana
Author-email: yrkau86@gmail.com
Classifier: Programming Language :: Python :: 3
Classifier: License :: OSI Approved :: MIT License
Classifier: Operating System :: OS Independent
License-File: LICENSE
Requires-Dist: split-folders
Requires-Dist: PyYAML
Requires-Dist: Click
